hm_python/__init__.py
hm_python/console.py
hm_python/wikipedia.py
hm_python-0.1.0.dist-info/entry_points.txt
hm_python-0.1.0.dist-info/LICENSE
hm_python-0.1.0.dist-info/WHEEL
hm_python-0.1.0.dist-info/METADATA
hm_python-0.1.0.dist-info/RECORD
