Metadata-Version: 2.1
Name: hm-python
Version: 0.1.0
Summary: The hypermodern Python project
Home-page: https://github.com/carlpayne/hm-python
License: MIT
Keywords: hypermodern
Author: Carl Payne
Author-email: cpayne@lightricks.com
Requires-Python: >=3.7,<4.0
Classifier: License :: OSI Approved :: MIT License
Classifier: Programming Language :: Python :: 3
Classifier: Programming Language :: Python :: 3.7
Classifier: Programming Language :: Python :: 3.8
Requires-Dist: click (>=8.1.3,<9.0.0)
Requires-Dist: desert (>=2020.11.18,<2021.0.0)
Requires-Dist: marshmallow (>=3.17.1,<4.0.0)
Requires-Dist: requests (>=2.28.1,<3.0.0)
Requires-Dist: types-click (>=7.1.8,<8.0.0)
Project-URL: Repository, https://github.com/carlpayne/hm-python
